text_chunker/__init__.py
text_chunker/text_chunker.py
text_chunker-0.2.1.dist-info/METADATA
text_chunker-0.2.1.dist-info/WHEEL
text_chunker-0.2.1.dist-info/licenses/LICENSE
text_chunker-0.2.1.dist-info/RECORD
