Metadata-Version: 2.1
Name: text_chunker
Version: 0.2.1
Summary: A Python class that takes in long text as input and divides it into shorter chunks no longer than a specified length.
Project-URL: Homepage, https://github.com/rpawk/text_chunker
Project-URL: Bug Tracker, https://github.com/rpawk/text_chunker/issues
Author-email: rpawk <rpawizardk@gmail.com>
License-File: LICENSE
Classifier: License :: OSI Approved :: MIT License
Classifier: Operating System :: OS Independent
Classifier: Programming Language :: Python :: 3
Requires-Python: >=3.5
